llmchatlinker/__init__.py
llmchatlinker/api.py
llmchatlinker/client.py
llmchatlinker/main.py
llmchatlinker/main_without_api.py
llmchatlinker/message_queue.py
llmchatlinker/orchestrator.py
llmchatlinker/units/__init__.py
llmchatlinker/units/chat_manage_unit.py
llmchatlinker/units/control_unit.py
llmchatlinker/units/database_manage_unit.py
llmchatlinker/units/llm_manage_unit.py
llmchatlinker/units/user_manage_unit.py
llmchatlinker-0.1.3.dist-info/LICENSE
llmchatlinker-0.1.3.dist-info/METADATA
llmchatlinker-0.1.3.dist-info/WHEEL
llmchatlinker-0.1.3.dist-info/entry_points.txt
llmchatlinker-0.1.3.dist-info/top_level.txt
llmchatlinker-0.1.3.dist-info/RECORD
