Metadata-Version: 2.1
Name: llmchatlinker
Version: 0.1.3
Summary: LLMChatLinker is a Middleware SDK designed to facilitate interaction between clients and Large Language Models (LLMs).
Author-email: Changjae Lee <changjae@buffalo.edu>
Maintainer-email: Changjae Lee <changjae@buffalo.edu>
License: MIT License
Project-URL: Documentation, https://github.com/xlab-ub/LLMChatLinker#readme
Project-URL: Repository, https://github.com/xlab-ub/LLMChatLinker.git
Project-URL: Issues, https://github.com/xlab-ub/LLMChatLinker/issues
Keywords: LLM,middleware,SDK,chat,API,python-package
Classifier: Development Status :: 4 - Beta
Classifier: Programming Language :: Python :: 3
Requires-Python: >=3.8
License-File: LICENSE
Requires-Dist: sqlalchemy
Requires-Dist: psycopg2-binary
Requires-Dist: pika
Requires-Dist: fastapi <=0.115.4
Requires-Dist: uvicorn
Requires-Dist: requests
Requires-Dist: python-slugify
Provides-Extra: testing
Requires-Dist: pytest ; extra == 'testing'
Requires-Dist: pytest-cov ; extra == 'testing'
Requires-Dist: tox ; extra == 'testing'
Requires-Dist: python-dotenv ; extra == 'testing'
